{
	"id": 1159,
	"denkmalbereich": "Braunschweiger Straße",
	"objektart": "Wohnhaus",
	"denkmalverzeichnisId": 1320,
	"image": "http://denkmalverzeichnis.magdeburg.de/RPWebMM/DENKMALE/BILDER8/5659.jpg",
	"anschrift": "Braunschweiger Straße 10",
	"objektbezeichnung": null,
	"description": "Viergeschossiger Putzbau der Neorenaissance mit über zwei Stockwerke reichender Hervorhebung der äußeren Fensterachsen, entstanden 1880er Jahre, durch seine repräsentative Fassadengestaltung zusammen mit Nr. 9 besonders straßenbildprägender Bestandteil innerhalb eines städtebaulich und kulturell-künstlerisch besonderen, geschlossen erhaltenen Straßenzuges der Gründerzeit in Magdeburg.\r\n\r\n(10.07.2008)",
	"stadteil": "Sudenburg",
	"lng": 11.603288,
	"lat": 52.112803
}