{
	"id": 2019,
	"denkmalbereich": "-----",
	"objektart": "Wohnhaus",
	"denkmalverzeichnisId": 2217,
	"image": "http://denkmalverzeichnis.magdeburg.de/RPWebMM/DENKMALE/BILDER7/5339.jpg",
	"anschrift": "Dorotheenstraße 2",
	"objektbezeichnung": null,
	"description": "Viergeschossiger siebenachsiger Putzbau im Stil der Neorenaissance erbaut ca. 1880 für C.W. Schindler von F. Oelze in gerader, sehr enger und lichtarmer Straßenflucht, die Fassadengestaltung im für Ende der 1870er, Anfang 1880er Jahre typischen antikisierenden Stil, flache Bandrustika im ersten Obergeschoss, einfache Kragplatten und Dreiecksgiebel als Fensterverdachungen, der Fassadenstuck an den beiden linken äußeren Achsen verloren, straßenbildprägendes Beispiel einfacher gründerzeitlicher Wohnverhältnisse im Industriequartier Buckau\r\n\r\n(10.07.2008)",
	"stadteil": "Buckau",
	"lng": 11.638875,
	"lat": 52.108244
}