{
	"id": 2343,
	"denkmalbereich": "Helmstedter Straße",
	"objektart": "Wohnhaus",
	"denkmalverzeichnisId": 2552,
	"image": "http://denkmalverzeichnis.magdeburg.de/RPWebMM/DENKMALE/BILDER3/2388.jpg",
	"anschrift": "Helmstedter Straße 12",
	"objektbezeichnung": null,
	"description": "Stattlicher viergeschossiger Ziegelbau von acht Achsen Breite im Stil der Neorenaissance erbaut ca. 1870/80, Erdgeschoss rustiziert, Fenster in den Obergeschossen mit Segmentbogen- und Dreiecksgiebeln, weiter Dachvorstand mit Konsolsteinen, als baulicher Bestandteil des komplett erhaltenen gründerzeitlichen Straßenzuges von städtebaulicher Bedeutung und stadtgeschichtlichem Wert.\r\n\r\n(10.07.2008)",
	"stadteil": "Sudenburg",
	"lng": 11.602802,
	"lat": 52.114686
}