{
	"id": 2948,
	"denkmalbereich": "-----",
	"objektart": "Wohnhaus",
	"denkmalverzeichnisId": 3191,
	"image": "http://denkmalverzeichnis.magdeburg.de/RPWebMM/DENKMALE/BILDER7/5338.jpg",
	"anschrift": "Dorotheenstraße 1",
	"objektbezeichnung": null,
	"description": "Viergeschossiger Putzbau mit reich gegliederter Fassade im Stil der Neorenaissance erbaut ca. 1880/1890, mit dem benachbarten Haus Nr. 2 eine straßenbildprägende Baugruppe bildend, bemerkenswert als Beispiel eines einfachen gründerzeitlichen Wohnhauses in typischer Blockrandbebauung im historischen Industriequartier Buckau.\r\n\r\n(10.07.2008)",
	"stadteil": "Buckau",
	"lng": 11.639086,
	"lat": 52.108315
}