{
	"id": 3306,
	"denkmalbereich": "Südliches Stadtzentrum",
	"objektart": "Wohnhaus",
	"denkmalverzeichnisId": 3578,
	"image": "http://denkmalverzeichnis.magdeburg.de/RPWebMM/DENKMALE/BILDER4/3139.jpg",
	"anschrift": "Hegelstraße 15",
	"objektbezeichnung": null,
	"description": "Repräsentativer fünfgeschossiger Putzbau im Neobarock, erbaut 1887, Entwurf von Bauherrn Maurermeister Griesemann, auffallend die beiden sehr hohen unteren, fast die Hälfte der Fassade einnehmenden Geschosse auf hohem Souterrain, hier Putzrustika, darüber horizontale Putzrillung, Fassaden prägend der zweiachsige Mittelrisalit mit Schweifgiebel und drei Säulen mit korinthischen Kapitellen, besonderer Dekor hier das gekröpfte Profilgesims sowie die Sprenggiebel, der Risalit ab dem zweiten Obergeschoss balkonartig vorragend, die Decke des Vestibüls mit stuckierten Rollwerkkartuschen und Puttenköpfen, als architektonischer Bestandteil der nahezu komplett erhaltenen Straße gehobener, großbürgerlicher Wohnbebauung von städtebaulicher Relevanz.\r\n\r\n(10.07.2008)",
	"stadteil": "Altstadt",
	"lng": 11.630789,
	"lat": 52.120385
}