{
	"id": 138,
	"denkmalbereich": "Südliches Stadtzentrum",
	"objektart": "Mahnmal",
	"denkmalverzeichnisId": 213,
	"image": "http://denkmalverzeichnis.magdeburg.de/RPWebMM/DENKMALE/BILDER/0403.jpg",
	"anschrift": "Steubenallee ",
	"objektbezeichnung": "Gedenkstätte für die Opfer des Faschismus im Steub",
	"description": "Mahnmal für den Widerstand gegen den Nationalsozialismus in der Parkanlage an der Steubenallee, von Bildhauer Eberhard Roßdeutscher (1921 - 1980) geschaffenes Ehrenmal für 62 von den Nationalsozialisten ermordeten Magdeburger Widerstandskämpfer, enthüllt am 8.Mai 1965, ca. 10m x 5m große, rechteckige, stehende Betonwand mit drei auf die Spitze gestellten, gleichseitigen, dreieckigen Aussparungen, symbolisierend die VVN (Vereinigung der Verfolgten des Nazi-Regimes), auf die Betonwand montiert ein hochrechteckiges, durchbrochenes Bronzerelief mit szenischen Darstellungen aus dem Magdeburger Widerstandskampf, auf der rechteckigen, mit Fußbodenplatten versiegelten Fläche vor der Betonwand eine größere behauene quadratische Bodenplatte mit den Namen der ermordeten Magdeburger Widerstandskämpfer in alphabetischer Reihenfolge.\r\n\r\n(10.07.2008)",
	"stadteil": "Altstadt",
	"lng": 11.630543,
	"lat": 52.114863
}