{
	"id": 2816,
	"denkmalbereich": "-----",
	"objektart": "Wohnhaus",
	"denkmalverzeichnisId": 3051,
	"image": "http://denkmalverzeichnis.magdeburg.de/RPWebMM/DENKMALE/BILDER4/2457.jpg",
	"anschrift": "Wilhelm-Kobelt-Straße 6",
	"objektbezeichnung": null,
	"description": "Dreigeschossiger Putzbau, erbaut 1913, bemerkenswert als Beispiel eines bürgerlichen Mietswohnhauses in Formen des späten Jugendstils, die Straßenfassade mit breitem Kastenerker und seitlichen kleinen Balkons, sparsamer Jugendstildekor am Eingang und im Brüstungsbereich der Fenster, straßenbildprägend im Ensemble mit benachbarten Wohnhäusern gleichen Stils, innen die ursprüngliche zweispännige Grundrissstruktur mit Drei- und Vierzimmerwohnungen erhalten, im Flur bauzeitliche dekorative Fenster mit Bleiverglasung.\r\n\r\n(10.07.2008)",
	"stadteil": "Stadtfeld Ost",
	"lng": 11.608238,
	"lat": 52.124881
}