{
	"id": 3039,
	"denkmalbereich": "-----",
	"objektart": "Wohnhaus",
	"denkmalverzeichnisId": 3292,
	"image": "http://denkmalverzeichnis.magdeburg.de/RPWebMM/DENKMALE/BILDER2/1414.jpg",
	"anschrift": "Schillerstraße 31",
	"objektbezeichnung": null,
	"description": "Dreigeschossiger Putzbau neoklassizistischer Formensprache mit hohem Mansarddach und gebogenem Dacherker erbaut 1912 für Bauunternehmer Albert Fischer, Entwurf wohl Reinhold Radisch, Balkone von zwei Erkern eingeschlossen, Fassadengestaltung mit großflächiger Pilastergliederung und von der Erkersohle frei hängenden Festons, bemerkenswertes und typisches Stadtteil-Wohnhaus für gehobene bürgerliche Wohnbedürfnisse aus der Zeit vor dem Ersten Weltkrieg, von straßenbildprägender Bedeutung innerhalb der neoklassizistischen Bebauung im Nordabschnitt der Schillerstraße.\r\n\r\n(10.07.2008)",
	"stadteil": "Stadtfeld Ost",
	"lng": 11.613157,
	"lat": 52.139101
}