{
	"id": 3274,
	"denkmalbereich": "-----",
	"objektart": "Wohnhaus",
	"denkmalverzeichnisId": 3545,
	"image": "http://denkmalverzeichnis.magdeburg.de/RPWebMM/DENKMALE/BILDER4/2777.jpg",
	"anschrift": "Winckelmannstraße 8",
	"objektbezeichnung": null,
	"description": "Drei- bis viergeschossige eklektizistische Ziegelputzbauten mit als Einheit gestalteter Straßenansicht und mächtigem Zwerchgiebel und Erkern im Stil des Art deco, erbaut 1907 nach Plänen des Architekten Max Suppelna für Bauunternehmer Paul Recke, Fassadengestaltung mit Stilelementen der deutschen Renaissance und des Schweizer Stils, das Dachgeschoss inzwischen ausgebaut, symmetrische, lebendige und farbige Fassadengestaltung durch die Verwendung von hellem Putz im Kontrast mit architektonischen Gliederungselementen aus roten und grün glasierten Ziegeln, im spitzen Winkel aus der Fassadenflucht hervortretende Erker und kleine Fachwerkgiebel über Risaliten, die Risalite und Erker jeweils mit seitlichen Balkonen, variierende Fensterbreiten mit kleinteiliger Binnengliederung, die sehr belebte Fassade mit herausragender malerischer Qualität architekturgeschichtlich bedeutsam als Unikum innerhalb der geschlossenen Nachbarbebauung, von straßenbilddominierender Erscheinung in unmittelbarer Kreuzungsnähe.\r\n\r\n(10.07.2008)",
	"stadteil": "Stadtfeld Ost",
	"lng": 11.610348,
	"lat": 52.12494
}