{
	"id": 4267,
	"denkmalbereich": "Südliches Stadtzentrum",
	"objektart": "Archiv",
	"denkmalverzeichnisId": 4677,
	"image": "http://denkmalverzeichnis.magdeburg.de/RPWebMM/DENKMALE/BILDER7/5090.jpg",
	"anschrift": "Hegelstraße 25",
	"objektbezeichnung": null,
	"description": "Als Königliches Staatsarchiv erbaut 1907/08 nach Entwurf der Kreisbauinspektion Magdeburg (Idee von Oberbaurat Georg Thür, Umsetzung von Regierungsbaurat Willy Schuhmann und Hermann Harms), großzügiger Putzbau mit Werksteingliederung in schlichten, gotisierenden Formen auf L-förmigem Grundriss, prägend für das architektonische Erscheinungsbild die steilen Satteldächer und Stufengiebel in malerisch-asymmetrischer Anordnung, paarige Anordnung der Fenster mit steinernen Mittelpfosten, der zur Elbseite sich erstreckende Magazinflügel kenntlich an niedrigen Geschosshöhen und eng gestellten Fensteröffnungen, innen Eisenkonstruktion, Wandtäfelungen und Wandmalereien sowie alte Türen erhalten, städtebaulich bedeutsam im Ensemble mit den unmittelbar benachbarten historischen Schulgebäuden (siehe Hegelstraße 22 und Geißlerstraße 4), straßenbildprägender Bestandteil der Hegelstraße, des bedeutendsten gründerzeitlichen Straßenzugs in Magdeburg.\r\n\r\n(10.07.2008)",
	"stadteil": "Altstadt",
	"lng": 11.629678,
	"lat": 52.118115
}